cqh_file_watcher/__init__.py
cqh_file_watcher/__main__.py
cqh_file_watcher/command_caller.py
cqh_file_watcher/conf.py
cqh_file_watcher/run.py
cqh_file_watcher/util.py
cqh_file_watcher-0.0.41.dist-info/LICENSE
cqh_file_watcher-0.0.41.dist-info/METADATA
cqh_file_watcher-0.0.41.dist-info/WHEEL
cqh_file_watcher-0.0.41.dist-info/entry_points.txt
cqh_file_watcher-0.0.41.dist-info/top_level.txt
cqh_file_watcher-0.0.41.dist-info/RECORD
