Metadata-Version: 2.1
Name: cqh-file-watcher
Version: 0.0.41
Summary: tools like vscode file-watcher but for command only
Home-page: https://github.com/chen19901225/cqh_file_watcher
Author: chenqinghe
Author-email: 1832866299@qq.com
License: UNKNOWN
Platform: UNKNOWN
Classifier: Programming Language :: Python :: 3
Classifier: License :: OSI Approved :: MIT License
Classifier: Operating System :: Unix
Requires-Python: >=3.6
License-File: LICENSE
Requires-Dist: pyinotify
